bootcamp_utils/__init__.py
bootcamp_utils/bioinfo_dicts.py
bootcamp_utils/hv_defaults.py
bootcamp_utils/na_utils.py
bootcamp_utils/viz.py
bootcamp_utils-0.0.7.dist-info/LICENSE
bootcamp_utils-0.0.7.dist-info/METADATA
bootcamp_utils-0.0.7.dist-info/WHEEL
bootcamp_utils-0.0.7.dist-info/top_level.txt
bootcamp_utils-0.0.7.dist-info/RECORD
