Metadata-Version: 2.1
Name: bootcamp-utils
Version: 0.0.7
Summary: Utilities for use in the Introduction to Programming in the Biological Sciences Bootcamp.
Home-page: https://github.com/justinbois/bootcamp_utils
Author: Justin Bois
Author-email: bois@caltech.edu
License: UNKNOWN
Platform: UNKNOWN
Classifier: Development Status :: 3 - Alpha
Classifier: Intended Audience :: Education
Classifier: License :: OSI Approved :: MIT License
Classifier: Natural Language :: English
Classifier: Programming Language :: Python :: 3
Classifier: Programming Language :: Python :: 3.6
Classifier: Programming Language :: Python :: 3.7
License-File: LICENSE
Requires-Dist: bokeh (>=2.0.0)
